Metadata-Version: 2.1
Name: classification-report
Version: 1.0.0
Summary: This repo helps to track model Weights, Biases and Gradients during training with loss tracking and gives detailed insight for Classification-Model Evaluation
Home-page: https://github.com/aman5319/Classification-Report
Author: Aman Pandey
Author-email: amanpandey5319@gmail.com
License: GPLv3
Project-URL: Documentation, https://classification-report.readthedocs.io/en/latest/
Project-URL: Source, https://github.com/aman5319/Classification-Report
Project-URL: Bug Trackers, https://github.com/aman5319/Classification-Report/issues
Keywords: Model-weight-tracking Tensorboard Tensorboard-visualization Model-Evaluation Loss-Tracking Metrics-Visualization Classification-Model
Platform: UNKNOWN
Classifier: Development Status :: 5 - Production/Stable
Classifier: Intended Audience :: Developers
Classifier: Intended Audience :: Education
Classifier: Intended Audience :: Science/Research
Classifier: License :: OSI Approved :: GNU General Public License v3 or later (GPLv3+)
Classifier: Natural Language :: English
Classifier: Operating System :: OS Independent
Classifier: Programming Language :: Python :: 3
Classifier: Programming Language :: Python :: 3.6
Classifier: Programming Language :: Python :: 3.7
Classifier: Topic :: Scientific/Engineering :: Artificial Intelligence
Requires-Python: >=3.6.0
Provides-Extra: dev
